{
  "content": "Enhanced",
  "dlc": true,
  "images": {
    "item": "../img/item/hive-mind.png"
  },
  "resources": {
    "lootlemon": "https://www.lootlemon.com/weapon/hive-mind-bl1",
    "wiki": "https://borderlands.fandom.com/wiki/Hive_Mind"
  },
  "name": "Hive Mind",
  "type": "Launcher",
  "description": "The Hive Mind is a Legendary Gearbox launcher from Borderlands 1 Enhanced Edition that fires three rockets in rapid succession per trigger pull. You can stop the burst early by reloading or meleeing to conserve ammo.",
  "manufacturer": [
    "Gearbox"
  ],
  "rarity": [
    "Legendary"
  ],
  "special": {
    "red": "That's gonna leave a Marx",
    "description": "Fires a 3-round burst of rockets with increased damage and magazine size but slower reload speed."
  },
  "max": {
    "damage": 5722,
    "accuracy": 73.3,
    "fire_rate": 1.5,
    "mag_size": 6,
    "level": 69
  },
  "source": [
    {
      "name": "Crawmerax",
      "tags": [
        "Raid Boss",
        "Craw's Lair"
      ]
    },
    {
      "name": "Destroyer Chest",
      "tags": [
        "Chest",
        "The Vault"
      ]
    },
    {
      "name": "Skagzilla",
      "tags": [
        "Unique Enemy",
        "DAHL Headland"
      ]
    }
  ]
}
