{
  "game": "borderlands2",
  "category": "relics",
  "content": "Base Game",
  "dlc": false,
  "image": "/img/games/borderlands2/relics/moxxis-endowment.png",
  "resources": {
    "lootlemon": "https://www.lootlemon.com/bonus-item/moxxis-endowment-bl2",
    "wiki": "https://borderlands.fandom.com/wiki/Moxxi's_Endowment"
  },
  "name": "Moxxi's Endowment",
  "slug": "moxxis-endowment",
  "type": "Universal",
  "description": "A unique Eridian relic that increases combat experience gained from enemy kills, making it a leveling tool rather than a combat relic. Its value drops once leveling speed matters less than the combat bonuses you give up in the relic slot.",
  "manufacturers": [
    "Eridian"
  ],
  "rarities": [
    "Rare"
  ],
  "sources": [
    {
      "name": "The Good, The Bad and the Mordecai",
      "tags": [
        "Quest",
        "The Dust"
      ]
    }
  ],
  "special": {
    "description": "Increases combat XP gained from killing enemies, with the bonus increasing as the relic's level rises."
  },
  "notes": "It is awarded for completing The Good, the Bad, and the Mordecai. The experience bonus increases with the relic's level, so later versions are stronger but still compete with more powerful combat relics.",
  "abilities": [
    "Increases experience gained by killing enemies."
  ],
  "max": {
    "level": 90
  }
}
