{
  "game": "borderlands2",
  "category": "weapons",
  "content": "Base Game",
  "dlc": false,
  "image": "/img/games/borderlands2/weapons/home-security.png",
  "resources": {
    "wiki": "https://borderlands.fandom.com/wiki/Home_Security"
  },
  "name": "Home Security",
  "slug": "home-security",
  "type": "Shotgun",
  "description": "Home Security always rolls with its matching Tediore barrel. It is a fairly middle of the road shotgun, trading the brand's typical ammo efficiency for reduced damage versus other Tediore shotguns. As with other Tediore shotguns, reloading throws the gun in a long forward arc.",
  "manufacturers": [
    "Tediore"
  ],
  "rarities": [
    "Common",
    "Uncommon",
    "Rare",
    "Epic"
  ],
  "elements": [
    "Incendiary",
    "Shock",
    "Corrosive",
    "Slag"
  ],
  "notes": "Drops at random from any appropriate loot source.",
  "sources": [
    {
      "name": "World Drop",
      "tags": [
        "General",
        "Any suitable loot source"
      ]
    }
  ]
}